gopen.py
gopen-0.6.6.dist-info/LICENSE.txt
gopen-0.6.6.dist-info/METADATA
gopen-0.6.6.dist-info/WHEEL
gopen-0.6.6.dist-info/top_level.txt
gopen-0.6.6.dist-info/RECORD
