Metadata-Version: 2.1
Name: gopen
Version: 0.6.6
Summary: A generic context manager for readable files.
Home-page: https://github.com/simomarsili/gopen
Author: Simone Marsili
Author-email: simo.marsili@gmail.com
License: BSD 3-Clause
Platform: UNKNOWN
Classifier: Development Status :: 3 - Alpha
Classifier: License :: OSI Approved :: BSD License
Classifier: Programming Language :: Python :: 3
Classifier: Programming Language :: Python :: 3.4
Classifier: Programming Language :: Python :: 3.5
Classifier: Programming Language :: Python :: 3.6
Requires-Dist: six
Requires-Dist: python-magic
Provides-Extra: test
Requires-Dist: pytest ; extra == 'test'
